{
"meta":{"test_sets":[],"test_metrics":[],"learn_metrics":[{"best_value":"Min","name":"RMSE"}],"launch_mode":"Train","parameters":"","iteration_count":100,"learn_sets":["learn"],"name":"experiment"},
"iterations":[
{"learn":[14.005006],"iteration":0,"passed_time":0.0009948618136,"remaining_time":0.09849131954},
{"learn":[13.14441192],"iteration":1,"passed_time":0.001313607589,"remaining_time":0.06436677185},
{"learn":[12.34258257],"iteration":2,"passed_time":0.001614686598,"remaining_time":0.0522082},
{"learn":[11.64527793],"iteration":3,"passed_time":0.001893223906,"remaining_time":0.04543737375},
{"learn":[11.02766183],"iteration":4,"passed_time":0.00223771934,"remaining_time":0.04251666746},
{"learn":[10.43485794],"iteration":5,"passed_time":0.002603214496,"remaining_time":0.04078369376},
{"learn":[9.890641275],"iteration":6,"passed_time":0.003111082764,"remaining_time":0.04133295672},
{"learn":[9.492161212],"iteration":7,"passed_time":0.003419786672,"remaining_time":0.03932754673},
{"learn":[9.105082953],"iteration":8,"passed_time":0.003756532209,"remaining_time":0.03798271456},
{"learn":[8.674157135],"iteration":9,"passed_time":0.004143985073,"remaining_time":0.03729586566},
{"learn":[8.341743544],"iteration":10,"passed_time":0.004483146578,"remaining_time":0.0362727314},
{"learn":[8.049372916],"iteration":11,"passed_time":0.004829891982,"remaining_time":0.03541920787},
{"learn":[7.757318612],"iteration":12,"passed_time":0.005159596612,"remaining_time":0.03452960809},
{"learn":[7.522206899],"iteration":13,"passed_time":0.005541216554,"remaining_time":0.03403890169},
{"learn":[7.297756655],"iteration":14,"passed_time":0.005908586684,"remaining_time":0.03348199121},
{"learn":[7.088359431],"iteration":15,"passed_time":0.006269914895,"remaining_time":0.0329170532},
{"learn":[6.882113791],"iteration":16,"passed_time":0.006597660551,"remaining_time":0.0322121074},
{"learn":[6.704728832],"iteration":17,"passed_time":0.006944113959,"remaining_time":0.03163429692},
{"learn":[6.563881962],"iteration":18,"passed_time":0.007284901442,"remaining_time":0.03105668509},
{"learn":[6.418790279],"iteration":19,"passed_time":0.007617189038,"remaining_time":0.03046875615},
{"learn":[6.315756953],"iteration":20,"passed_time":0.007937517792,"remaining_time":0.02986018598},
{"learn":[6.210157751],"iteration":21,"passed_time":0.008276971292,"remaining_time":0.02934562549},
{"learn":[6.115058449],"iteration":22,"passed_time":0.008740715146,"remaining_time":0.02926239418},
{"learn":[6.014819884],"iteration":23,"passed_time":0.00907762668,"remaining_time":0.02874581782},
{"learn":[5.93117229],"iteration":24,"passed_time":0.009494330157,"remaining_time":0.02848299047},
{"learn":[5.844857622],"iteration":25,"passed_time":0.009795951159,"remaining_time":0.02788078407},
{"learn":[5.771145213],"iteration":26,"passed_time":0.01011073799,"remaining_time":0.02733643974},
{"learn":[5.704018229],"iteration":27,"passed_time":0.01044265059,"remaining_time":0.02685253008},
{"learn":[5.665806474],"iteration":28,"passed_time":0.01076548031,"remaining_time":0.02635686558},
{"learn":[5.616500369],"iteration":29,"passed_time":0.01108051713,"remaining_time":0.02585453998},
{"learn":[5.558023666],"iteration":30,"passed_time":0.01142017963,"remaining_time":0.0254191095},
{"learn":[5.510080976],"iteration":31,"passed_time":0.01175375921,"remaining_time":0.02497673832},
{"learn":[5.468747792],"iteration":32,"passed_time":0.01219496236,"remaining_time":0.02475946904},
{"learn":[5.429275534],"iteration":33,"passed_time":0.0125317079,"remaining_time":0.02432625651},
{"learn":[5.402117324],"iteration":34,"passed_time":0.01285916156,"remaining_time":0.02388130004},
{"learn":[5.367635151],"iteration":35,"passed_time":0.01322265674,"remaining_time":0.02350694531},
{"learn":[5.345181232],"iteration":36,"passed_time":0.01359015187,"remaining_time":0.02313998832},
{"learn":[5.319151269],"iteration":37,"passed_time":0.01408181235,"remaining_time":0.02297558857},
{"learn":[5.296134146],"iteration":38,"passed_time":0.01451376463,"remaining_time":0.02270101647},
{"learn":[5.269629003],"iteration":39,"passed_time":0.0148778008,"remaining_time":0.0223167012},
{"learn":[5.251147059],"iteration":40,"passed_time":0.01525212884,"remaining_time":0.0219481854},
{"learn":[5.248003302],"iteration":41,"passed_time":0.01536733531,"remaining_time":0.02122155829},
{"learn":[5.232376509],"iteration":42,"passed_time":0.01583332914,"remaining_time":0.02098836653},
{"learn":[5.213524255],"iteration":43,"passed_time":0.01629915696,"remaining_time":0.02074438159},
{"learn":[5.189691584],"iteration":44,"passed_time":0.01695144032,"remaining_time":0.02071842705},
{"learn":[5.166052198],"iteration":45,"passed_time":0.01736280986,"remaining_time":0.02038242897},
{"learn":[5.140406659],"iteration":46,"passed_time":0.01782880369,"remaining_time":0.02010482118},
{"learn":[5.118929684],"iteration":47,"passed_time":0.01839083724,"remaining_time":0.01992340701},
{"learn":[5.108792602],"iteration":48,"passed_time":0.01874199958,"remaining_time":0.01950697916},
{"learn":[5.098141225],"iteration":49,"passed_time":0.01921349333,"remaining_time":0.01921349333},
{"learn":[5.085926393],"iteration":50,"passed_time":0.01951898928,"remaining_time":0.01875353872},
{"learn":[5.067816804],"iteration":51,"passed_time":0.01987352559,"remaining_time":0.01834479285},
{"learn":[5.049834901],"iteration":52,"passed_time":0.02032260263,"remaining_time":0.01802193064},
{"learn":[5.03838627],"iteration":53,"passed_time":0.02080930418,"remaining_time":0.0177264443},
{"learn":[5.033534248],"iteration":54,"passed_time":0.02112538399,"remaining_time":0.01728440508},
{"learn":[5.023726885],"iteration":55,"passed_time":0.02151625381,"remaining_time":0.01690562799},
{"learn":[5.01290392],"iteration":56,"passed_time":0.02210982894,"remaining_time":0.01667934464},
{"learn":[5.005569127],"iteration":57,"passed_time":0.02260782234,"remaining_time":0.0163711817},
{"learn":[4.989969032],"iteration":58,"passed_time":0.02300715005,"remaining_time":0.01598801953},
{"learn":[4.976762446],"iteration":59,"passed_time":0.02331077103,"remaining_time":0.01554051402},
{"learn":[4.967222715],"iteration":60,"passed_time":0.02363197577,"remaining_time":0.01510896811},
{"learn":[4.954407599],"iteration":61,"passed_time":0.02396672133,"remaining_time":0.01468928082},
{"learn":[4.942125056],"iteration":62,"passed_time":0.02438229882,"remaining_time":0.0143197628},
{"learn":[4.930230716],"iteration":63,"passed_time":0.02473162819,"remaining_time":0.01391154086},
{"learn":[4.921695642],"iteration":64,"passed_time":0.02507254067,"remaining_time":0.01350059882},
{"learn":[4.906405625],"iteration":65,"passed_time":0.02544370176,"remaining_time":0.01310736151},
{"learn":[4.894330248],"iteration":66,"passed_time":0.02577928031,"remaining_time":0.01269725746},
{"learn":[4.88211557],"iteration":67,"passed_time":0.02611656784,"remaining_time":0.01229014957},
{"learn":[4.877946398],"iteration":68,"passed_time":0.02643898056,"remaining_time":0.01187838257},
{"learn":[4.863182126],"iteration":69,"passed_time":0.0269190572,"remaining_time":0.0115367388},
{"learn":[4.84646533],"iteration":70,"passed_time":0.02743667534,"remaining_time":0.01120652936},
{"learn":[4.838014752],"iteration":71,"passed_time":0.02780575345,"remaining_time":0.01081334856},
{"learn":[4.82981137],"iteration":72,"passed_time":0.0281566238,"remaining_time":0.01041409373},
{"learn":[4.817094767],"iteration":73,"passed_time":0.02849074437,"remaining_time":0.01001026153},
{"learn":[4.808314151],"iteration":74,"passed_time":0.02879694831,"remaining_time":0.00959898277},
{"learn":[4.796235023],"iteration":75,"passed_time":0.0291820682,"remaining_time":0.009215389959},
{"learn":[4.784434534],"iteration":76,"passed_time":0.02958122991,"remaining_time":0.008835951793},
{"learn":[4.774402487],"iteration":77,"passed_time":0.03002359905,"remaining_time":0.008468194604},
{"learn":[4.76731896],"iteration":78,"passed_time":0.03038655224,"remaining_time":0.008077437937},
{"learn":[4.75934113],"iteration":79,"passed_time":0.03078617194,"remaining_time":0.007696542986},
{"learn":[4.754106378],"iteration":80,"passed_time":0.03115500105,"remaining_time":0.00730796321},
{"learn":[4.744002932],"iteration":81,"passed_time":0.03177261787,"remaining_time":0.006974477093},
{"learn":[4.731700554],"iteration":82,"passed_time":0.03236927596,"remaining_time":0.006629851703},
{"learn":[4.723284153],"iteration":83,"passed_time":0.03280014525,"remaining_time":0.006247646714},
{"learn":[4.712232782],"iteration":84,"passed_time":0.03319763998,"remaining_time":0.005858407055},
{"learn":[4.703046867],"iteration":85,"passed_time":0.03356046917,"remaining_time":0.005463332191},
{"learn":[4.698601855],"iteration":86,"passed_time":0.03388021493,"remaining_time":0.005062560852},
{"learn":[4.692429407],"iteration":87,"passed_time":0.03422158541,"remaining_time":0.004666579828},
{"learn":[4.675027364],"iteration":88,"passed_time":0.03454495612,"remaining_time":0.004269601318},
{"learn":[4.662368584],"iteration":89,"passed_time":0.03503311665,"remaining_time":0.003892568517},
{"learn":[4.646206172],"iteration":90,"passed_time":0.0353466125,"remaining_time":0.003495818818},
{"learn":[4.641245848],"iteration":91,"passed_time":0.03570248278,"remaining_time":0.00310456372},
{"learn":[4.633900435],"iteration":92,"passed_time":0.0360480202,"remaining_time":0.002713291843},
{"learn":[4.624738236],"iteration":93,"passed_time":0.03668592774,"remaining_time":0.002341654962},
{"learn":[4.612798287],"iteration":94,"passed_time":0.03702529825,"remaining_time":0.001948699908},
{"learn":[4.605222001],"iteration":95,"passed_time":0.03740162726,"remaining_time":0.001558401136},
{"learn":[4.601725912],"iteration":96,"passed_time":0.03774458071,"remaining_time":0.001167358166},
{"learn":[4.59722371],"iteration":97,"passed_time":0.03815824123,"remaining_time":0.0007787396169},
{"learn":[4.580235665],"iteration":98,"passed_time":0.03850594462,"remaining_time":0.0003889489356},
{"learn":[4.57591791],"iteration":99,"passed_time":0.03887893968,"remaining_time":0}
]}